shiroin.py
shiroin/__init__.py
shiroin-1.1.2.dist-info/LICENSE
shiroin-1.1.2.dist-info/METADATA
shiroin-1.1.2.dist-info/WHEEL
shiroin-1.1.2.dist-info/top_level.txt
shiroin-1.1.2.dist-info/RECORD
