Metadata-Version: 2.1
Name: shiroin
Version: 1.1.2
Summary: Software for proving inequalities
Home-page: https://github.com/urojony/shiroin
Author: Grzegorz Adamski
Author-email: grzes-a1@o2.pl
License: BSD
Platform: UNKNOWN
Classifier: License :: OSI Approved :: BSD License
Classifier: Operating System :: OS Independent
Classifier: Intended Audience :: Science/Research
Classifier: Programming Language :: Python :: 3
Classifier: Topic :: Scientific/Engineering :: Mathematics
Requires-Python: >=3.5
Requires-Dist: scipy (>=0.15)
Requires-Dist: sympy
